pyzenith-0.3.5.dist-info/licenses/LICENSE
zenith/__init__.py
zenith/_zenith_core.cpython-312-x86_64-linux-gnu.so
zenith/api.py
zenith/backends.py
zenith/build_cuda.py
zenith/cli.py
zenith/compat.py
zenith/errors.py
zenith/adapters/__init__.py
zenith/adapters/base.py
zenith/adapters/jax_adapter.py
zenith/adapters/onnx_adapter.py
zenith/adapters/pytorch_adapter.py
zenith/adapters/tensorflow_adapter.py
zenith/backends/__init__.py
zenith/backends/base.py
zenith/backends/cuda_backend.py
zenith/backends/oneapi_backend.py
zenith/backends/registry.py
zenith/backends/rocm_backend.py
zenith/backends/xla_backend.py
zenith/core/__init__.py
zenith/core/graph_ir.py
zenith/core/hlo_lowering.py
zenith/core/node.py
zenith/core/tensor.py
zenith/core/types.py
zenith/execution/__init__.py
zenith/execution/context.py
zenith/execution/interpreter.py
zenith/execution/registry.py
zenith/execution/operators/__init__.py
zenith/execution/operators/activation_ops.py
zenith/execution/operators/conv_ops.py
zenith/execution/operators/math_ops.py
zenith/execution/operators/norm_ops.py
zenith/execution/operators/shape_ops.py
zenith/execution/operators/tensor_ops.py
zenith/inference/__init__.py
zenith/integrations/__init__.py
zenith/integrations/torch_dynamo.py
zenith/jax/__init__.py
zenith/jax/checkpointing.py
zenith/jax/memory_manager.py
zenith/jax/mixed_precision.py
zenith/jax/onnx_export.py
zenith/jax/primitives.py
zenith/memory/__init__.py
zenith/memory/gradient_checkpointing.py
zenith/memory/native_checkpointing.py
zenith/monitoring/__init__.py
zenith/monitoring/dashboard.py
zenith/monitoring/exporter.py
zenith/monitoring/server.py
zenith/observability/__init__.py
zenith/observability/context.py
zenith/observability/events.py
zenith/observability/gpu_metrics.py
zenith/observability/logger.py
zenith/observability/metrics.py
zenith/optimization/__init__.py
zenith/optimization/advanced_fusion.py
zenith/optimization/autotuner.py
zenith/optimization/benchmark.py
zenith/optimization/benchmark_utils.py
zenith/optimization/fusion_pass.py
pyzenith-0.3.5.dist-info/METADATA
pyzenith-0.3.5.dist-info/WHEEL
pyzenith-0.3.5.dist-info/entry_points.txt
pyzenith-0.3.5.dist-info/top_level.txt
pyzenith-0.3.5.dist-info/RECORD
