Metadata-Version: 2.4
Name: pyzenith
Version: 0.3.5
Summary: Cross-Platform ML Optimization Framework with ONNX Interpreter
Author-email: Wahyu Ardiansyah <wahyuardiansyah1903@gmail.com>
Maintainer-email: Wahyu Ardiansyah <wahyuardiansyah1903@gmail.com>
License: Apache-2.0
Project-URL: Homepage, https://github.com/vibeswithkk/zenith
Project-URL: Documentation, https://zenith.dev/docs
Project-URL: Repository, https://github.com/vibeswithkk/zenith
Project-URL: Issues, https://github.com/vibeswithkk/zenith/issues
Keywords: machine-learning,deep-learning,optimization,compiler,pytorch,tensorflow,jax,onnx,cuda,inference
Classifier: Development Status :: 3 - Alpha
Classifier: Intended Audience :: Developers
Classifier: Intended Audience :: Science/Research
Classifier: License :: OSI Approved :: Apache Software License
Classifier: Programming Language :: Python :: 3
Classifier: Programming Language :: C++
Classifier: Topic :: Scientific/Engineering :: Artificial Intelligence
Classifier: Topic :: Software Development :: Compilers
Requires-Python: >=3.9
License-File: LICENSE
Requires-Dist: numpy>=1.20.0
Provides-Extra: onnx
Requires-Dist: onnx>=1.14.0; extra == "onnx"
Requires-Dist: onnxruntime>=1.15.0; extra == "onnx"
Provides-Extra: pytorch
Requires-Dist: torch>=2.0.0; extra == "pytorch"
Provides-Extra: tensorflow
Requires-Dist: tensorflow>=2.12.0; extra == "tensorflow"
Requires-Dist: tf2onnx>=1.14.0; extra == "tensorflow"
Provides-Extra: jax
Requires-Dist: jax>=0.4.0; extra == "jax"
Requires-Dist: jaxlib>=0.4.0; extra == "jax"
Provides-Extra: all
Requires-Dist: pyzenith[jax,onnx,pytorch,tensorflow]; extra == "all"
Provides-Extra: monitoring
Requires-Dist: pynvml>=11.0.0; extra == "monitoring"
Provides-Extra: dev
Requires-Dist: pytest>=7.0.0; extra == "dev"
Requires-Dist: pytest-cov>=4.0.0; extra == "dev"
Requires-Dist: black>=23.0.0; extra == "dev"
Requires-Dist: isort>=5.12.0; extra == "dev"
Requires-Dist: mypy>=1.0.0; extra == "dev"
Requires-Dist: ruff>=0.1.0; extra == "dev"
Requires-Dist: hypothesis>=6.0.0; extra == "dev"
Requires-Dist: pynvml>=11.0.0; extra == "dev"
Dynamic: license-file
